src/__init__.py
src/manage.py
src/requirements.txt
src/config/__init__.py
src/config/asgi.py
src/config/settings.py
src/config/urls.py
src/config/wsgi.py
src/input/forms.py
src/input/params.py
src/input/__pycache__/params.cpython-39.pyc
src/interface/__init__.py
src/interface/admin.py
src/interface/apps.py
src/interface/models.py
src/interface/tests.py
src/interface/urls.py
src/interface/views.py
src/interface/migrations/__init__.py
src/templates/base.html
src/templates/interface/index.html
src/templates/snippets/base_css.html
django_machine_learning_user_interface-0.0.0.18.dist-info/LICENSE
django_machine_learning_user_interface-0.0.0.18.dist-info/METADATA
django_machine_learning_user_interface-0.0.0.18.dist-info/WHEEL
django_machine_learning_user_interface-0.0.0.18.dist-info/top_level.txt
django_machine_learning_user_interface-0.0.0.18.dist-info/RECORD
