Metadata-Version: 2.1
Name: django-machine-learning-user-interface
Version: 0.0.0.18
Summary: A package to help developers build front end user interfaces for machine learning models.
Home-page: https://github.com/Phikolomzi-Gugwana/django-machine-learning-user-interface.git
Author: Phikolomzi Gugwana
Author-email: ggwphi001@myuct.ac.za
Maintainer: Phikolomzi Gugwana
Maintainer-email: ggwphi001@myuct.ac.za
License: BSD License
Keywords: python django machine-learning user-interface
Platform: UNKNOWN
Classifier: License :: OSI Approved :: BSD License
Classifier: Development Status :: 2 - Pre-Alpha
Classifier: Intended Audience :: Developers
Classifier: Programming Language :: Python :: 3
Classifier: Operating System :: Unix
Classifier: Operating System :: MacOS :: MacOS X
Classifier: Operating System :: Microsoft :: Windows
Classifier: Topic :: Software Development :: Libraries :: Python Modules
